partial_backup/__init__.py
partial_backup/__main__.py
partial_backup/_version.py
partial_backup/backup.py
partial_backup/mbdb.py
partial_backup-0.0.2.dist-info/METADATA
partial_backup-0.0.2.dist-info/WHEEL
partial_backup-0.0.2.dist-info/entry_points.txt
partial_backup-0.0.2.dist-info/top_level.txt
partial_backup-0.0.2.dist-info/RECORD
