Metadata-Version: 2.4
Name: partial-backup
Version: 0.0.2
Summary: Metadata-Aware Partial Backup Creator
Project-URL: Homepage, https://github.com/doronz88/partial-backup
Project-URL: Bug Reports, https://github.com/doronz88/partial-backup/issues
Keywords: ios,backup,partial-backup
Classifier: Development Status :: 5 - Production/Stable
Classifier: Programming Language :: Python :: 3
Classifier: Programming Language :: Python :: 3.9
Classifier: Programming Language :: Python :: 3.10
Classifier: Programming Language :: Python :: 3.11
Classifier: Programming Language :: Python :: 3.12
Classifier: Programming Language :: Python :: 3.13
Classifier: Programming Language :: Python :: 3 :: Only
Requires-Python: >=3.9
Requires-Dist: rich
Requires-Dist: typer
Provides-Extra: test
Requires-Dist: pytest; extra == "test"
Requires-Dist: pytest-asyncio; extra == "test"
